{
  "videos": [
    {
      "input": [
        {
          "i": "resources/00_WhatsACrypto-Intro.mp4"
        }
      ],
      "output": "build/00_.mp4"
    },
    {
      "input": [
        {
          "i": "resources/06_blockchain.mp4"
        }
      ],
      "output": "build/01_.mp4"
    },
    {
      "input": [
        {
          "i": "resources/07_visualQue.mp4"
        }
      ],
      "output": "build/02_.mp4"
    },
    {
      "input": [
        {
          "i": "resources/08_TransactionFees.mp4"
        }
      ],
      "output": "build/03_.mp4"
    },
    {
      "input": [
        {
          "i": "resources/09_PKI.mp4"
        }
      ],
      "output": "build/04_.mp4"
    },
    {
      "input": [
        {
          "i": "resources/99_thanks.mp4"
        }
      ],
      "output": "build/05_.mp4"
    }
  ]
}
